{
	"start_message": { "other": "Start message here" },
	"select_language": { "other": "Select your preferred language" },
	"help_info": { "other": "Help message here" },
	"session_title": { "other": "Session id: {{.SessionId}}\nParticipants: {{.Participants}}\n" },
	"back_to_list": { "other": "« Back to the list" },
	"user_settings_title": { "other": "Settings\n<b>Language</b>: {{.Lang}}" },
	"change_language": { "other": "Change Language" },
	"command_canceled": { "other": "If there was some action I canceled it" }
}
